rcplant/__init__.py
rcplant/_constants.py
rcplant/_container.py
rcplant/_conveyor.py
rcplant/_dataset.py
rcplant/_material.py
rcplant/_recycling_plant.py
rcplant/_sensor.py
rcplant/_simulation.py
rcplant/_types.py
rcplant/__pycache__/__init__.cpython-39.pyc
rcplant/__pycache__/_constants.cpython-39.pyc
rcplant/__pycache__/_container.cpython-39.pyc
rcplant/__pycache__/_conveyor.cpython-39.pyc
rcplant/__pycache__/_dataset.cpython-39.pyc
rcplant/__pycache__/_material.cpython-39.pyc
rcplant/__pycache__/_recycling_plant.cpython-39.pyc
rcplant/__pycache__/_sensor.cpython-39.pyc
rcplant/__pycache__/_simulation.cpython-39.pyc
rcplant/__pycache__/_types.cpython-39.pyc
rcplant/data/.DS_Store
rcplant/data/FTIR Plastic Database.xlsx
rcplant/data/Raman Plastic Database.xlsx
rcplant-1.1.3.dist-info/LICENSE
rcplant-1.1.3.dist-info/METADATA
rcplant-1.1.3.dist-info/WHEEL
rcplant-1.1.3.dist-info/top_level.txt
rcplant-1.1.3.dist-info/RECORD
