Metadata-Version: 2.1
Name: rcplant
Version: 1.1.3
Summary: Recycling Plant Simulator
Home-page: 
Author: Mohammadreza Rostam, Rongxuan Du
Author-email: reza.rostam@mech.ubc.ca
License: UNKNOWN
Platform: UNKNOWN
Classifier: Development Status :: 5 - Production/Stable
Classifier: License :: Free for non-commercial use
Classifier: Operating System :: OS Independent
Classifier: Programming Language :: Python :: 3.8
Classifier: Topic :: Scientific/Engineering
Requires-Python: >=3.7
License-File: LICENSE
Requires-Dist: pandas (>=1.3.4)
Requires-Dist: openpyxl (>=3.0.9)
Requires-Dist: numpy (>=1.21.5)
